godx/__init__.py
godx/godx.py
godx-1.0.3.dist-info/METADATA
godx-1.0.3.dist-info/WHEEL
godx-1.0.3.dist-info/entry_points.txt
godx-1.0.3.dist-info/top_level.txt
godx-1.0.3.dist-info/RECORD
